boolean.v
`timescale 1ns / 1ps
//////////////////////////////////////////////////////////////////////////////////
// Company: 
// Engineer: Edmond Febrinicko Armay
// 
// Create Date: 2022-07-28 08:28:52 PM
// Design Name: 
// Module Name: boolean
// Project Name: 
// Target Devices: 
// Tool Versions: 
// Description: 
// program of continuous assignment
// Dependencies: 
// 
// Revision:
// Revision 0.01 - File Created
// Additional Comments:
// 
//////////////////////////////////////////////////////////////////////////////////
module boolean (
    input a,
    input b,
    input c,
    output F
);
    assign F = (~a & ~b & c) | (a & ~b & c);
endmodule

boolean_TB.v
`timescale 1ns / 1ps
//////////////////////////////////////////////////////////////////////////////////
// Company: 
// Engineer: Edmond Febrinicko Armay
// 
// Create Date: 2022-07-29 08:29:20 PM
// Design Name: 
// Module Name: boolean_TB
// Project Name: 
// Target Devices: 
// Tool Versions: 
// Description: 
// testbench for boolean program
// Dependencies: 
// 
// Revision:
// Revision 0.01 - File Created
// Additional Comments:
// 
//////////////////////////////////////////////////////////////////////////////////
module boolean_TB ();
    reg a, b, c;
    wire F;
    boolean DUT_boolean(a, b, c, f);
    initial begin
        $dumpfile("boolean.vcd");
        $dumpvars(0, boolean_TB);
        {a, b, c} = 0; #10;
        {a, b, c} = 1; #10;
        {a, b, c} = 2; #10;
        {a, b, c} = 3; #10;
        {a, b, c} = 4; #10;
        {a, b, c} = 5; #10;
        {a, b, c} = 6; #10;
        {a, b, c} = 7; #10;
        $stop;
    end
endmodule

boolean.vcd
$date
	Fri Jul 29 14:43:24 2022
$end
$version
	Icarus Verilog
$end
$timescale
	1ps
$end
$scope module boolean_TB $end
$var wire 1 ! f $end
$var reg 1 " a $end
$var reg 1 # b $end
$var reg 1 $ c $end
$scope module DUT_boolean $end
$var wire 1 ! F $end
$var wire 1 " a $end
$var wire 1 # b $end
$var wire 1 $ c $end
$upscope $end
$upscope $end
$enddefinitions $end
#0
$dumpvars
0$
0#
0"
0!
$end
#10000
1!
1$
#20000
0!
1#
0$
#30000
1$
#40000
1"
0#
0$
#50000
1!
1$
#60000
0!
1#
0$
#70000
1$
