demux_1_to_4.v
`timescale 1ns / 1ps
//////////////////////////////////////////////////////////////////////////////////
// Company: 
// Engineer: Edmond Febrinicko Armay
// 
// Create Date: 2022-07-28 06:40:33 PM
// Design Name: 
// Module Name: demux_1_to_4
// Project Name: 
// Target Devices: 
// Tool Versions: 
// Description: 
// demultiplexer 1 to 4 program
// Dependencies: 
// 
// Revision:
// Revision 0.01 - File Created
// Additional Comments:
// 
//////////////////////////////////////////////////////////////////////////////////
module demux_1_to_4 (
    input I,
    input [1:0] sel,
    output reg [3:0] Y
);
    always @ (sel, I)
    case (sel)
        2'b00: Y = {3'b0, I};
        2'b01: Y = {2'b0, I, 1'b0};
        2'b10: Y = {1'b0, I, 2'b0};
        2'b11: Y = {I, 3'b0};
    endcase
endmodule

demux_TB.v
`timescale 1ns / 1ps
//////////////////////////////////////////////////////////////////////////////////
// Company: 
// Engineer: Edmond Febrinicko Armay
// 
// Create Date: 2022-07-28 07:16:09 PM
// Design Name: 
// Module Name: demux_TB
// Project Name: 
// Target Devices: 
// Tool Versions: 
// Description: 
// testbench for demultiplexer 1 to 4
// Dependencies: 
// 
// Revision:
// Revision 0.01 - File Created
// Additional Comments:
// 
//////////////////////////////////////////////////////////////////////////////////
module demux_TB ();
    reg a;
    reg [1:0] sel;
    wire [3:0] demux_out;
    demux_1_to_4 DUT_demux(a, sel, demux_out);
    initial begin
        $dumpfile("demux.vcd");
        $dumpvars(0, demux_TB);
        a = 0;
        sel = 0; #10;
        a = 1;  #10;
        a = 0;  #10;
        sel = 1; #10;
        a = 1;  #10;
        a = 0;  #10;
        sel = 2; #10;
        a = 1;  #10;
        a = 0;  #10;
        sel = 3; #10;
        a = 1;  #10;
        a = 0;  #10;
        $stop;
    end
endmodule

demux.vcd
$date
	Thu Jul 28 18:06:46 2022
$end
$version
	Icarus Verilog
$end
$timescale
	1ps
$end
$scope module demux_TB $end
$var wire 4 ! demux_out [3:0] $end
$var reg 1 " a $end
$var reg 2 # sel [1:0] $end
$scope module DUT_demux $end
$var wire 1 " I $end
$var wire 2 $ sel [1:0] $end
$var reg 4 % Y [3:0] $end
$upscope $end
$upscope $end
$enddefinitions $end
#0
$dumpvars
b0 %
b0 $
b0 #
0"
b0 !
$end
#10000
b1 !
b1 %
1"
#20000
b0 !
b0 %
0"
#30000
b1 #
b1 $
#40000
b10 !
b10 %
1"
#50000
b0 !
b0 %
0"
#60000
b10 #
b10 $
#70000
b100 !
b100 %
1"
#80000
b0 !
b0 %
0"
#90000
b11 #
b11 $
#100000
b1000 !
b1000 %
1"
#110000
b0 !
b0 %
0"
