half_adder.v
`timescale 1ns / 1ps
//////////////////////////////////////////////////////////////////////////////////
// Company: 
// Engineer: Edmond Febrinicko Armay
// 
// Create Date: 2022-07-25 04:24:58 PM
// Design Name: 
// Module Name: half_adder
// Project Name: 
// Target Devices: 
// Tool Versions: 
// Description: 
// half adder program
// Dependencies: 
// 
// Revision:
// Revision 0.01 - File Created
// Additional Comments:
// 
//////////////////////////////////////////////////////////////////////////////////
module half_adder (
    input A,
    input B,
    output S,
    output Cout
);
    and(Cout, A, B);
    xor(S, A, B);
endmodule

full_adder.v
`timescale 1ns / 1ps
//////////////////////////////////////////////////////////////////////////////////
// Company: 
// Engineer: Edmond Febrinicko Armay
// 
// Create Date: 2022-07-25 04:24:58 PM
// Design Name: 
// Module Name: full_adder
// Project Name: 
// Target Devices: 
// Tool Versions: 
// Description: 
// full adder program
// Dependencies: 
// 
// Revision:
// Revision 0.01 - File Created
// Additional Comments:
// 
//////////////////////////////////////////////////////////////////////////////////

module full_adder (
    input A, input B, input Cin, output S, output Cout
);
    wire P, G, H;
    half_adder ha1(A, B, P, G);
    half_adder ha2(
        .A(P),
        .B(Cin),
        .S(S),
        .Cout(H)
        );
    or(Cout, G, H);
endmodule

sim_full_adder.v
`timescale 1ns / 1ps
//////////////////////////////////////////////////////////////////////////////////
// Company: 
// Engineer: Edmond Febrinicko Armay
// 
// Create Date: 2022-07-25 04:28:04 PM
// Design Name: 
// Module Name: sim_full_adder
// Project Name: 
// Target Devices: 
// Tool Versions: 
// Description: 
// simulating a full adder
// Dependencies: 
// 
// Revision:
// Revision 0.01 - File Created
// Additional Comments:
// 
//////////////////////////////////////////////////////////////////////////////////
module sim_full_adder ();
    reg a, b, c;
    wire [1:0] s;
    full_adder FA(a, b, c, s[0], s[1]);
    initial begin
        $dumpfile("FA.vcd");
        $dumpvars(0, sim_full_adder);
        {a, b, c}=0; #5;
        {a, b, c}=1; #5;
        {a, b, c}=2; #5;
        {a, b, c}=3; #5;
        {a, b, c}=4; #5;
        {a, b, c}=5; #5;
        {a, b, c}=6; #5;
        {a, b, c}=7; #5;
        $stop;
    end
endmodule

FA.vcd
$date
	Mon Jul 25 08:01:23 2022
$end
$version
	Icarus Verilog
$end
$timescale
	1ps
$end
$scope module sim_full_adder $end
$var wire 2 ! s [1:0] $end
$var reg 1 " a $end
$var reg 1 # b $end
$var reg 1 $ c $end
$scope module FA $end
$var wire 1 " A $end
$var wire 1 # B $end
$var wire 1 $ Cin $end
$var wire 1 % Cout $end
$var wire 1 & S $end
$var wire 1 ' P $end
$var wire 1 ( H $end
$var wire 1 ) G $end
$scope module ha1 $end
$var wire 1 " A $end
$var wire 1 # B $end
$var wire 1 ) Cout $end
$var wire 1 ' S $end
$upscope $end
$scope module ha2 $end
$var wire 1 ' A $end
$var wire 1 $ B $end
$var wire 1 ( Cout $end
$var wire 1 & S $end
$upscope $end
$upscope $end
$upscope $end
$enddefinitions $end
#0
$dumpvars
0)
0(
0'
0&
0%
0$
0#
0"
b0 !
$end
#5000
b1 !
1&
1$
#10000
1'
b1 !
1&
1#
0$
#15000
1%
1(
b10 !
0&
1$
#20000
0%
0(
b1 !
1&
1"
0#
0$
#25000
1%
1(
b10 !
0&
1$
#30000
1)
0'
0(
b10 !
0&
1#
0$
#35000
b11 !
1&
1$
