gate_level_simulation.v
`timescale 1ns / 1ps
//////////////////////////////////////////////////////////////////////////////////
// Company: 
// Engineer: 
// 
// Create Date: 10/13/2019 09:58:09 PM
// Design Name: 
// Module Name: gate_level_simulation
// Project Name: 
// Target Devices: 
// Tool Versions: 
// Description: 
// 
// Dependencies: 
// 
// Revision:
// Revision 0.01 - File Created
// Additional Comments:
// 
//////////////////////////////////////////////////////////////////////////////////


module gate_level_simulation();
    reg a,b,c,d,e;
    wire X,Y;
    
    nand my_gate(X,a,b,c);
    
    wire temp;
    xor(temp,d,e);
    not(Y,temp);

    initial begin
	$dumpfile("gate.vcd");
	$dumpvars(0, gate_level_simulation);
        {a,b,c} = 0;   
        {d,e}   = 0;   #2
        {a,b,c} = 1;   #2
        {a,b,c} = 2;   
        {d,e}   = 1;   #2
        {a,b,c} = 3;   #2
        {a,b,c} = 4;   
        {d,e}   = 2;   #2
        {a,b,c} = 5;   #2
        {a,b,c} = 6;   
        {d,e}   = 3;   #2
        {a,b,c} = 7;   #2
        $stop;  
    end 
endmodule

gate.vcd
$date
	Wed Jul 20 09:59:10 2022
$end
$version
	Icarus Verilog
$end
$timescale
	1ps
$end
$scope module gate_level_simulation $end
$var wire 1 ! X $end
$var wire 1 " Y $end
$var wire 1 # temp $end
$var reg 1 $ a $end
$var reg 1 % b $end
$var reg 1 & c $end
$var reg 1 ' d $end
$var reg 1 ( e $end
$upscope $end
$enddefinitions $end
#0
$dumpvars
0(
0'
0&
0%
0$
0#
1"
1!
$end
#2000
1&
#4000
0"
1#
1(
1%
0&
#6000
1&
#8000
1'
0(
1$
0%
0&
#10000
1&
#12000
1"
0#
1(
1%
0&
#14000
0!
1&
