logic.v
`timescale 1ns / 1ps
//////////////////////////////////////////////////////////////////////////////////
// Company: 
// Engineer: Edmond Febrinicko Armay
// 
// Create Date: 2022-07-29 02:55:40 PM
// Design Name: 
// Module Name: logic
// Project Name: 
// Target Devices: 
// Tool Versions: 
// Description: 
// program of blocking assignment
// Dependencies: 
// 
// Revision:
// Revision 0.01 - File Created
// Additional Comments:
// 
//////////////////////////////////////////////////////////////////////////////////
module LOGIC (
    input a,
    input b,
    input c,
    output reg z
);
    reg t1, t2;
    always @ (a, b, c) begin
        t1 = b & c;
        t2 = a & ~b;
        z = t1 | t2;
    end
endmodule

logic_TB.v
`timescale 1ns / 1ps
//////////////////////////////////////////////////////////////////////////////////
// Company: 
// Engineer: Edmond Febrinicko Armay
// 
// Create Date: 2022-07-29 07:04:42 PM
// Design Name: 
// Module Name: logic_TB
// Project Name: 
// Target Devices: 
// Tool Versions: 
// Description: 
// testbench for logic program
// Dependencies: 
// 
// Revision:
// Revision 0.01 - File Created
// Additional Comments:
// 
//////////////////////////////////////////////////////////////////////////////////
module logic_TB ();
    reg [2:0] in;
    wire out;
    LOGIC DUT_logic(in[2], in[1], in[0], out);
    initial begin
        $dumpfile("logic.vcd");
        $dumpvars(0, logic_TB);
        in = 0; #10;
        in = 1; #10;
        in = 2; #10;
        in = 3; #10;
        in = 4; #10;
        in = 5; #10;
        in = 6; #10;
        in = 7; #10;
        $stop;
    end
endmodule

logic.vcd
$date
	Fri Jul 29 16:41:59 2022
$end
$version
	Icarus Verilog
$end
$timescale
	1ps
$end
$scope module logic_TB $end
$var wire 1 ! out $end
$var reg 3 " in [2:0] $end
$scope module DUT_logic $end
$var wire 1 # a $end
$var wire 1 $ b $end
$var wire 1 % c $end
$var reg 1 & t1 $end
$var reg 1 ' t2 $end
$var reg 1 ! z $end
$upscope $end
$upscope $end
$enddefinitions $end
#0
$dumpvars
0'
0&
0%
0$
0#
b0 "
0!
$end
#10000
1%
b1 "
#20000
1$
0%
b10 "
#30000
1!
1&
1%
b11 "
#40000
1'
0&
1#
0$
0%
b100 "
#50000
1%
b101 "
#60000
0!
0'
1$
0%
b110 "
#70000
1!
1&
1%
b111 "
