mux_2_to_1.v
`timescale 1ns / 1ps
//////////////////////////////////////////////////////////////////////////////////
// Company: LinkedIn Learning
// Engineer: Eduardo Corpeño
// 
// Create Date: 11/07/2019 04:28:15 PM
// Design Name: 
// Module Name: mux_2_to_1
// Project Name: 
// Target Devices: 
// Tool Versions: 
// Description: 
// 
// Dependencies: 
// 
// Revision:
// Revision 0.01 - File Created
// Additional Comments:
// 
//////////////////////////////////////////////////////////////////////////////////
module mux_2_to_1 (
    input [1:0] I,
    input sel,
    output reg Y
);
    always @ (sel, I) begin
        if (sel == 0)
        Y = I[0];
        else
            Y = I[1];
    end
endmodule

mux_TB.v
`timescale 1ns / 1ps
//////////////////////////////////////////////////////////////////////////////////
// Company: 
// Engineer: Edmond Febrinicko Armay
// 
// Create Date: 2022-07-27 04:31:19 PM
// Design Name: 
// Module Name: mux_TB
// Project Name: 
// Target Devices: 
// Tool Versions: 
// Description: 
// testbench for multiplexer 2 to 1
// Dependencies: 
// 
// Revision:
// Revision 0.01 - File Created
// Additional Comments:
// 
//////////////////////////////////////////////////////////////////////////////////
module mux_TB ();
    reg a, b, sel;
    wire mux_out;
    mux_2_to_1 DUT_mux({b, a}, sel, mux_out);
    initial begin
        $dumpfile("mux.vcd");
        $dumpvars(0, mux_TB);
        a = 0; b = 0; sel = 0; #10;
        a = 1; b = 0; sel = 0; #10;
        a = 1; b = 0; sel = 0; #10;
        a = 1; b = 1; sel = 0; #10;
        a = 0; b = 0; sel = 0; #10;
        a = 1; b = 0; sel = 0; #10;
        a = 0; b = 1; sel = 0; #10;
        a = 1; b = 0; sel = 0; #10;
        a = 1; b = 0; sel = 1; #10;
        a = 1; b = 0; sel = 1; #10;
        a = 0; b = 0; sel = 1; #10;
        a = 1; b = 0; sel = 1; #10;
        a = 1; b = 0; sel = 1; #10;
        a = 1; b = 0; sel = 1; #10;
        a = 0; b = 1; sel = 1; #10;
        a = 1; b = 0; sel = 1; #10;
        $stop;
    end
endmodule

mux.vcd
$date
	Wed Jul 27 18:10:26 2022
$end
$version
	Icarus Verilog
$end
$timescale
	1ps
$end
$scope module mux_TB $end
$var wire 1 ! mux_out $end
$var reg 1 " a $end
$var reg 1 # b $end
$var reg 1 $ sel $end
$scope module DUT_mux $end
$var wire 2 % I [1:0] $end
$var wire 1 $ sel $end
$var reg 1 ! Y $end
$upscope $end
$upscope $end
$enddefinitions $end
#0
$dumpvars
b0 %
0$
0#
0"
0!
$end
#10000
1!
b1 %
1"
#30000
b11 %
1#
#40000
0!
0#
b0 %
0"
#50000
1!
b1 %
1"
#60000
0!
1#
b10 %
0"
#70000
1!
0#
b1 %
1"
#80000
0!
1$
#100000
b0 %
0"
#110000
b1 %
1"
#140000
1!
1#
b10 %
0"
#150000
0!
0#
b1 %
1"
