demux_1_to_4.v
`timescale 1ns / 1ps
//////////////////////////////////////////////////////////////////////////////////
// Company: 
// Engineer: Edmond Febrinicko Armay
// 
// Create Date: 2022-07-28 06:40:33 PM
// Design Name: 
// Module Name: demux_1_to_4
// Project Name: 
// Target Devices: 
// Tool Versions: 
// Description: 
// demultiplexer 1 to 4 program
// Dependencies: 
// 
// Revision:
// Revision 0.01 - File Created
// Additional Comments:
// 
//////////////////////////////////////////////////////////////////////////////////
module demux_1_to_4 (
    input I,
    input [1:0] sel,
    output reg [3:0] Y
);
    always @ (sel, I)
    case (sel)
        2'b00: Y = {3'b0, I};
        2'b01: Y = {2'b0, I, 1'b0};
        2'b10: Y = {1'b0, I, 2'b0};
        2'b11: Y = {I, 3'b0};
    endcase
endmodule

mux_2_to_1.v
`timescale 1ns / 1ps
//////////////////////////////////////////////////////////////////////////////////
// Company: LinkedIn Learning
// Engineer: Eduardo Corpeño
// 
// Create Date: 11/07/2019 04:28:15 PM
// Design Name: 
// Module Name: mux_2_to_1
// Project Name: 
// Target Devices: 
// Tool Versions: 
// Description: 
// 
// Dependencies: 
// 
// Revision:
// Revision 0.01 - File Created
// Additional Comments:
// 
//////////////////////////////////////////////////////////////////////////////////
module mux_2_to_1 (
    input [1:0] I,
    input sel,
    output reg Y
);
    always @ (sel, I) begin
        if (sel == 0)
        Y = I[0];
        else
            Y = I[1];
    end
endmodule

mux_demux_TB.v
`timescale 1ns / 1ns
//////////////////////////////////////////////////////////////////////////////////
// Company: 
// Engineer: Edmond Febrinicko Armay
// 
// Create Date: 2022-08-04 08:20:08 PM
// Design Name: 
// Module Name: mux_demux_TB
// Project Name: 
// Target Devices: 
// Tool Versions: 
// Description: 
// testbench program for multiplexer and demultiplexer
// Dependencies: 
// 
// Revision:
// Revision 0.01 - File Created
// Additional Comments:
// 
//////////////////////////////////////////////////////////////////////////////////
module mux_demux_TB ();
    reg clk_1MHz, clk_4MHz;
    reg sel1;
    reg [1:0] sel2;
    wire mux_out;
    wire [3:0] demux_out;
    mux_2_to_1 DUT_mux(
        .I({clk_4MHz, clk_1MHz}),
        .sel(sel1),
        .Y(mux_out)
    );
    demux_1_to_4 DUT_demux(
        .I(clk_1MHz),
        .sel(sel2),
        .Y(demux_out)
    );
    always #500 clk_1MHz = ~clk_1MHz;
    always #125 clk_4MHz = ~clk_4MHz;
    initial begin
        $dumpfile("mux_demux.vcd");
        $dumpvars(0, mux_demux_TB);
        clk_1MHz = 0;
        clk_4MHz = 0;
        sel1 = 0;
        sel2 = 0;
        #10_000;
        sel2 = 1;
        #10_000;
        sel1 = 1;
        sel2 = 2;
        #10_000;
        sel2 = 3;
        #10_000;
        $finish;
    end
endmodule

mux_demux.vcd
$date
	Thu Aug  4 16:27:10 2022
$end
$version
	Icarus Verilog
$end
$timescale
	1ps
$end
$scope module mux_demux_TB $end
$var wire 1 ! mux_out $end
$var wire 4 " demux_out [3:0] $end
$var reg 1 # clk_1MHz $end
$var reg 1 $ clk_4MHz $end
$var reg 1 % sel1 $end
$var reg 2 & sel2 [1:0] $end
$scope module DUT_demux $end
$var wire 1 # I $end
$var wire 2 ' sel [1:0] $end
$var reg 4 ( Y [3:0] $end
$upscope $end
$scope module DUT_mux $end
$var wire 2 ) I [1:0] $end
$var wire 1 % sel $end
$var reg 1 ! Y $end
$upscope $end
$upscope $end
$enddefinitions $end
#0
$dumpvars
b0 )
b0 (
b0 '
b0 &
0%
0$
0#
b0 "
0!
$end
#125000
b10 )
1$
#250000
b0 )
0$
#375000
b10 )
1$
#500000
1!
b1 "
b1 (
0$
b1 )
1#
#625000
b11 )
1$
#750000
b1 )
0$
#875000
b11 )
1$
#1000000
0!
b0 "
b0 (
0$
b0 )
0#
#1125000
b10 )
1$
#1250000
b0 )
0$
#1375000
b10 )
1$
#1500000
1!
b1 "
b1 (
0$
b1 )
1#
#1625000
b11 )
1$
#1750000
b1 )
0$
#1875000
b11 )
1$
#2000000
0!
b0 "
b0 (
0$
b0 )
0#
#2125000
b10 )
1$
#2250000
b0 )
0$
#2375000
b10 )
1$
#2500000
1!
b1 "
b1 (
0$
b1 )
1#
#2625000
b11 )
1$
#2750000
b1 )
0$
#2875000
b11 )
1$
#3000000
0!
b0 "
b0 (
0$
b0 )
0#
#3125000
b10 )
1$
#3250000
b0 )
0$
#3375000
b10 )
1$
#3500000
1!
b1 "
b1 (
0$
b1 )
1#
#3625000
b11 )
1$
#3750000
b1 )
0$
#3875000
b11 )
1$
#4000000
0!
b0 "
b0 (
0$
b0 )
0#
#4125000
b10 )
1$
#4250000
b0 )
0$
#4375000
b10 )
1$
#4500000
1!
b1 "
b1 (
0$
b1 )
1#
#4625000
b11 )
1$
#4750000
b1 )
0$
#4875000
b11 )
1$
#5000000
0!
b0 "
b0 (
0$
b0 )
0#
#5125000
b10 )
1$
#5250000
b0 )
0$
#5375000
b10 )
1$
#5500000
1!
b1 "
b1 (
0$
b1 )
1#
#5625000
b11 )
1$
#5750000
b1 )
0$
#5875000
b11 )
1$
#6000000
0!
b0 "
b0 (
0$
b0 )
0#
#6125000
b10 )
1$
#6250000
b0 )
0$
#6375000
b10 )
1$
#6500000
1!
b1 "
b1 (
0$
b1 )
1#
#6625000
b11 )
1$
#6750000
b1 )
0$
#6875000
b11 )
1$
#7000000
0!
b0 "
b0 (
0$
b0 )
0#
#7125000
b10 )
1$
#7250000
b0 )
0$
#7375000
b10 )
1$
#7500000
1!
b1 "
b1 (
0$
b1 )
1#
#7625000
b11 )
1$
#7750000
b1 )
0$
#7875000
b11 )
1$
#8000000
0!
b0 "
b0 (
0$
b0 )
0#
#8125000
b10 )
1$
#8250000
b0 )
0$
#8375000
b10 )
1$
#8500000
1!
b1 "
b1 (
0$
b1 )
1#
#8625000
b11 )
1$
#8750000
b1 )
0$
#8875000
b11 )
1$
#9000000
0!
b0 "
b0 (
0$
b0 )
0#
#9125000
b10 )
1$
#9250000
b0 )
0$
#9375000
b10 )
1$
#9500000
1!
b1 "
b1 (
0$
b1 )
1#
#9625000
b11 )
1$
#9750000
b1 )
0$
#9875000
b11 )
1$
#10000000
0!
b0 "
b0 (
0$
b0 )
0#
b1 &
b1 '
#10125000
b10 )
1$
#10250000
b0 )
0$
#10375000
b10 )
1$
#10500000
1!
b10 "
b10 (
0$
b1 )
1#
#10625000
b11 )
1$
#10750000
b1 )
0$
#10875000
b11 )
1$
#11000000
0!
b0 "
b0 (
0$
b0 )
0#
#11125000
b10 )
1$
#11250000
b0 )
0$
#11375000
b10 )
1$
#11500000
1!
b10 "
b10 (
0$
b1 )
1#
#11625000
b11 )
1$
#11750000
b1 )
0$
#11875000
b11 )
1$
#12000000
0!
b0 "
b0 (
0$
b0 )
0#
#12125000
b10 )
1$
#12250000
b0 )
0$
#12375000
b10 )
1$
#12500000
1!
b10 "
b10 (
0$
b1 )
1#
#12625000
b11 )
1$
#12750000
b1 )
0$
#12875000
b11 )
1$
#13000000
0!
b0 "
b0 (
0$
b0 )
0#
#13125000
b10 )
1$
#13250000
b0 )
0$
#13375000
b10 )
1$
#13500000
1!
b10 "
b10 (
0$
b1 )
1#
#13625000
b11 )
1$
#13750000
b1 )
0$
#13875000
b11 )
1$
#14000000
0!
b0 "
b0 (
0$
b0 )
0#
#14125000
b10 )
1$
#14250000
b0 )
0$
#14375000
b10 )
1$
#14500000
1!
b10 "
b10 (
0$
b1 )
1#
#14625000
b11 )
1$
#14750000
b1 )
0$
#14875000
b11 )
1$
#15000000
0!
b0 "
b0 (
0$
b0 )
0#
#15125000
b10 )
1$
#15250000
b0 )
0$
#15375000
b10 )
1$
#15500000
1!
b10 "
b10 (
0$
b1 )
1#
#15625000
b11 )
1$
#15750000
b1 )
0$
#15875000
b11 )
1$
#16000000
0!
b0 "
b0 (
0$
b0 )
0#
#16125000
b10 )
1$
#16250000
b0 )
0$
#16375000
b10 )
1$
#16500000
1!
b10 "
b10 (
0$
b1 )
1#
#16625000
b11 )
1$
#16750000
b1 )
0$
#16875000
b11 )
1$
#17000000
0!
b0 "
b0 (
0$
b0 )
0#
#17125000
b10 )
1$
#17250000
b0 )
0$
#17375000
b10 )
1$
#17500000
1!
b10 "
b10 (
0$
b1 )
1#
#17625000
b11 )
1$
#17750000
b1 )
0$
#17875000
b11 )
1$
#18000000
0!
b0 "
b0 (
0$
b0 )
0#
#18125000
b10 )
1$
#18250000
b0 )
0$
#18375000
b10 )
1$
#18500000
1!
b10 "
b10 (
0$
b1 )
1#
#18625000
b11 )
1$
#18750000
b1 )
0$
#18875000
b11 )
1$
#19000000
0!
b0 "
b0 (
0$
b0 )
0#
#19125000
b10 )
1$
#19250000
b0 )
0$
#19375000
b10 )
1$
#19500000
1!
b10 "
b10 (
0$
b1 )
1#
#19625000
b11 )
1$
#19750000
b1 )
0$
#19875000
b11 )
1$
#20000000
b0 "
b0 (
0!
0$
b0 )
0#
b10 &
b10 '
1%
#20125000
1!
b10 )
1$
#20250000
0!
b0 )
0$
#20375000
1!
b10 )
1$
#20500000
0!
b100 "
b100 (
0$
b1 )
1#
#20625000
1!
b11 )
1$
#20750000
0!
b1 )
0$
#20875000
1!
b11 )
1$
#21000000
0!
b0 "
b0 (
0$
b0 )
0#
#21125000
1!
b10 )
1$
#21250000
0!
b0 )
0$
#21375000
1!
b10 )
1$
#21500000
0!
b100 "
b100 (
0$
b1 )
1#
#21625000
1!
b11 )
1$
#21750000
0!
b1 )
0$
#21875000
1!
b11 )
1$
#22000000
0!
b0 "
b0 (
0$
b0 )
0#
#22125000
1!
b10 )
1$
#22250000
0!
b0 )
0$
#22375000
1!
b10 )
1$
#22500000
0!
b100 "
b100 (
0$
b1 )
1#
#22625000
1!
b11 )
1$
#22750000
0!
b1 )
0$
#22875000
1!
b11 )
1$
#23000000
0!
b0 "
b0 (
0$
b0 )
0#
#23125000
1!
b10 )
1$
#23250000
0!
b0 )
0$
#23375000
1!
b10 )
1$
#23500000
0!
b100 "
b100 (
0$
b1 )
1#
#23625000
1!
b11 )
1$
#23750000
0!
b1 )
0$
#23875000
1!
b11 )
1$
#24000000
0!
b0 "
b0 (
0$
b0 )
0#
#24125000
1!
b10 )
1$
#24250000
0!
b0 )
0$
#24375000
1!
b10 )
1$
#24500000
0!
b100 "
b100 (
0$
b1 )
1#
#24625000
1!
b11 )
1$
#24750000
0!
b1 )
0$
#24875000
1!
b11 )
1$
#25000000
0!
b0 "
b0 (
0$
b0 )
0#
#25125000
1!
b10 )
1$
#25250000
0!
b0 )
0$
#25375000
1!
b10 )
1$
#25500000
0!
b100 "
b100 (
0$
b1 )
1#
#25625000
1!
b11 )
1$
#25750000
0!
b1 )
0$
#25875000
1!
b11 )
1$
#26000000
0!
b0 "
b0 (
0$
b0 )
0#
#26125000
1!
b10 )
1$
#26250000
0!
b0 )
0$
#26375000
1!
b10 )
1$
#26500000
0!
b100 "
b100 (
0$
b1 )
1#
#26625000
1!
b11 )
1$
#26750000
0!
b1 )
0$
#26875000
1!
b11 )
1$
#27000000
0!
b0 "
b0 (
0$
b0 )
0#
#27125000
1!
b10 )
1$
#27250000
0!
b0 )
0$
#27375000
1!
b10 )
1$
#27500000
0!
b100 "
b100 (
0$
b1 )
1#
#27625000
1!
b11 )
1$
#27750000
0!
b1 )
0$
#27875000
1!
b11 )
1$
#28000000
0!
b0 "
b0 (
0$
b0 )
0#
#28125000
1!
b10 )
1$
#28250000
0!
b0 )
0$
#28375000
1!
b10 )
1$
#28500000
0!
b100 "
b100 (
0$
b1 )
1#
#28625000
1!
b11 )
1$
#28750000
0!
b1 )
0$
#28875000
1!
b11 )
1$
#29000000
0!
b0 "
b0 (
0$
b0 )
0#
#29125000
1!
b10 )
1$
#29250000
0!
b0 )
0$
#29375000
1!
b10 )
1$
#29500000
0!
b100 "
b100 (
0$
b1 )
1#
#29625000
1!
b11 )
1$
#29750000
0!
b1 )
0$
#29875000
1!
b11 )
1$
#30000000
0!
b0 "
b0 (
0$
b0 )
0#
b11 &
b11 '
#30125000
1!
b10 )
1$
#30250000
0!
b0 )
0$
#30375000
1!
b10 )
1$
#30500000
0!
b1000 "
b1000 (
0$
b1 )
1#
#30625000
1!
b11 )
1$
#30750000
0!
b1 )
0$
#30875000
1!
b11 )
1$
#31000000
0!
b0 "
b0 (
0$
b0 )
0#
#31125000
1!
b10 )
1$
#31250000
0!
b0 )
0$
#31375000
1!
b10 )
1$
#31500000
0!
b1000 "
b1000 (
0$
b1 )
1#
#31625000
1!
b11 )
1$
#31750000
0!
b1 )
0$
#31875000
1!
b11 )
1$
#32000000
0!
b0 "
b0 (
0$
b0 )
0#
#32125000
1!
b10 )
1$
#32250000
0!
b0 )
0$
#32375000
1!
b10 )
1$
#32500000
0!
b1000 "
b1000 (
0$
b1 )
1#
#32625000
1!
b11 )
1$
#32750000
0!
b1 )
0$
#32875000
1!
b11 )
1$
#33000000
0!
b0 "
b0 (
0$
b0 )
0#
#33125000
1!
b10 )
1$
#33250000
0!
b0 )
0$
#33375000
1!
b10 )
1$
#33500000
0!
b1000 "
b1000 (
0$
b1 )
1#
#33625000
1!
b11 )
1$
#33750000
0!
b1 )
0$
#33875000
1!
b11 )
1$
#34000000
0!
b0 "
b0 (
0$
b0 )
0#
#34125000
1!
b10 )
1$
#34250000
0!
b0 )
0$
#34375000
1!
b10 )
1$
#34500000
0!
b1000 "
b1000 (
0$
b1 )
1#
#34625000
1!
b11 )
1$
#34750000
0!
b1 )
0$
#34875000
1!
b11 )
1$
#35000000
0!
b0 "
b0 (
0$
b0 )
0#
#35125000
1!
b10 )
1$
#35250000
0!
b0 )
0$
#35375000
1!
b10 )
1$
#35500000
0!
b1000 "
b1000 (
0$
b1 )
1#
#35625000
1!
b11 )
1$
#35750000
0!
b1 )
0$
#35875000
1!
b11 )
1$
#36000000
0!
b0 "
b0 (
0$
b0 )
0#
#36125000
1!
b10 )
1$
#36250000
0!
b0 )
0$
#36375000
1!
b10 )
1$
#36500000
0!
b1000 "
b1000 (
0$
b1 )
1#
#36625000
1!
b11 )
1$
#36750000
0!
b1 )
0$
#36875000
1!
b11 )
1$
#37000000
0!
b0 "
b0 (
0$
b0 )
0#
#37125000
1!
b10 )
1$
#37250000
0!
b0 )
0$
#37375000
1!
b10 )
1$
#37500000
0!
b1000 "
b1000 (
0$
b1 )
1#
#37625000
1!
b11 )
1$
#37750000
0!
b1 )
0$
#37875000
1!
b11 )
1$
#38000000
0!
b0 "
b0 (
0$
b0 )
0#
#38125000
1!
b10 )
1$
#38250000
0!
b0 )
0$
#38375000
1!
b10 )
1$
#38500000
0!
b1000 "
b1000 (
0$
b1 )
1#
#38625000
1!
b11 )
1$
#38750000
0!
b1 )
0$
#38875000
1!
b11 )
1$
#39000000
0!
b0 "
b0 (
0$
b0 )
0#
#39125000
1!
b10 )
1$
#39250000
0!
b0 )
0$
#39375000
1!
b10 )
1$
#39500000
0!
b1000 "
b1000 (
0$
b1 )
1#
#39625000
1!
b11 )
1$
#39750000
0!
b1 )
0$
#39875000
1!
b11 )
1$
#40000000
0!
b0 "
b0 (
0$
b0 )
0#
