is_prime_procedural.v
`timescale 1ns / 1ps
//////////////////////////////////////////////////////////////////////////////////
// Company: Linkedin Learning
// Engineer: Eduardo Corpeño, Edmond Febrinicko Armay
// 
// Create Date: 10/28/2019 08:37:01 PM
// Design Name: 
// Module Name: is_prime_procedural
// Project Name: 
// Target Devices: 
// Tool Versions: 
// Description: 
// program of prime number using blocking method (always keyword)
// Dependencies: 
// 
// Revision:
// Revision 0.01 - File Created
// Additional Comments:
// 
//////////////////////////////////////////////////////////////////////////////////
module is_prime_procedural (
    input c,
    input b,
    input a,
    output reg P
);
    wire [2:0] cba;
    assign cba = {c, b, a};
    always @ (cba)
    if (cba == 3'd2 || cba == 3'd3 || cba == 3'd5 || cba == 3'd7) begin
        P = 1'b1;
    end
    else
        P = 1'b0;
endmodule

is_prime_TB.v
`timescale 1ns / 1ps
//////////////////////////////////////////////////////////////////////////////////
// Company: 
// Engineer: Edmond Febrinicko Armay
// 
// Create Date: 2022-07-31 08:39:46 PM
// Design Name: 
// Module Name: is_prime_TB
// Project Name: 
// Target Devices: 
// Tool Versions: 
// Description: 
// testbench for prime number program
// Dependencies: 
// 
// Revision:
// Revision 0.01 - File Created
// Additional Comments:
// 
//////////////////////////////////////////////////////////////////////////////////
module is_prime_TB ();
    reg [2:0] cba;
    wire prime;
    reg pass;
    //is_prime_gates DUT_IP(cba[2], cba[1], cba[0], prime);
    //is_prime_boolean DUT_IP(cba[2], cba[1], cba[0], prime);
    is_prime_procedural DUT_IP(cba[2], cba[1], cba[0], prime);
    initial begin
        //$dumpfile("prime_gates.vcd");
        //$dumpfile("prime_boolean.vcd");
        $dumpfile("prime_procedural.vcd");
        $dumpvars(0, is_prime_TB);
        cba = 0; pass = 1; #10;
        pass = (prime == 1)? 0:pass;
        cba = 1; #10;
        pass = (prime == 1)? 0:pass;
        cba = 2; #10;
        pass = (prime == 0)? 0:pass;
        cba = 3; #10;
        pass = (prime == 0)? 0:pass;
        cba = 4; #10;
        pass = (prime == 1)? 0:pass;
        cba = 5; #10;
        pass = (prime == 0)? 0:pass;
        cba = 6; #10;
        pass = (prime == 1)? 0:pass;
        cba = 7; #10;
        pass = (prime == 0)? 0:pass;
        if (pass) begin
            $display("Nice job, you aced the challenge! Pat yourself on the back!");
        end
        else
            $display("There is something wrong with your module. Don't give up!");
        $stop;
    end
endmodule

prime_procedural.vcd
$date
	Mon Aug  1 18:12:30 2022
$end
$version
	Icarus Verilog
$end
$timescale
	1ps
$end
$scope module is_prime_TB $end
$var wire 1 ! prime $end
$var reg 3 " cba [2:0] $end
$var reg 1 # pass $end
$scope module DUT_IP $end
$var wire 1 $ a $end
$var wire 1 % b $end
$var wire 1 & c $end
$var wire 3 ' cba [2:0] $end
$var reg 1 ! P $end
$upscope $end
$upscope $end
$enddefinitions $end
#0
$dumpvars
b0 '
0&
0%
0$
1#
b0 "
0!
$end
#10000
b1 '
1$
b1 "
#20000
1!
1%
b10 '
0$
b10 "
#30000
b11 '
1$
b11 "
#40000
0!
1&
0%
b100 '
0$
b100 "
#50000
1!
b101 '
1$
b101 "
#60000
0!
1%
b110 '
0$
b110 "
#70000
1!
b111 '
1$
b111 "
